{
    "UxmlGuid": "257abef5dd0e81444b3205280f4fb9d4",
    "UxmlPath": "Assets/test.uxml",
    "CanvasX": 0,
    "CanvasY": 0,
    "CanvasWidth": 1101,
    "CanvasHeight": 514,
    "MatchGameView": true,
    "ZoomScale": 1.0,
    "PanOffset": {
        "x": 146.0855255126953,
        "y": 84.19033813476563
    },
    "ColorModeBackgroundOpacity": 1.0,
    "ImageModeCanvasBackgroundOpacity": 1.0,
    "CameraModeCanvasBackgroundOpacity": 1.0,
    "EnableCanvasBackground": false,
    "CanvasBackgroundMode": 0,
    "CanvasBackgroundColor": {
        "r": 0.0,
        "g": 0.0,
        "b": 0.0,
        "a": 255.0
    },
    "CanvasBackgroundImage": {
        "instanceID": 0
    },
    "CanvasBackgroundImageScaleMode": 1,
    "CanvasBackgroundCameraName": ""
}